remotejoystick/__init__.py
remotejoystick/config.py
remotejoystick/local.py
remotejoystick/main.py
remotejoystick/receiver.py
remotejoystick/sender.py
remotejoystick/server.py
remotejoystick/models/__init__.py
remotejoystick/models/communication/__init__.py
remotejoystick/models/communication/jssocket.py
remotejoystick/models/communication/receiver.py
remotejoystick/models/communication/sender.py
remotejoystick/models/communication/server.py
remotejoystick/models/controller/__init__.py
remotejoystick/models/controller/joystick.py
remotejoystick/models/controller/keyboard.py
remotejoystick/models/controller/test.py
remotejoystick-0.0.6.dist-info/DESCRIPTION.rst
remotejoystick-0.0.6.dist-info/METADATA
remotejoystick-0.0.6.dist-info/RECORD
remotejoystick-0.0.6.dist-info/WHEEL
remotejoystick-0.0.6.dist-info/entry_points.txt
remotejoystick-0.0.6.dist-info/metadata.json
remotejoystick-0.0.6.dist-info/top_level.txt
