Metadata-Version: 2.0
Name: remotejoystick
Version: 0.0.6
Summary: Remote joysticks can be used as locals ones.
Home-page: https://github.com/littlecodersh/remotejoystick
Author: LittleCoder
Author-email: i7meavnktqegm1b@qq.com
License: MIT
Keywords: joystick remote socket
Platform: UNKNOWN
Classifier: Development Status :: 3 - Alpha
Classifier: Intended Audience :: Developers
Classifier: Topic :: Software Development :: Libraries :: Python Modules
Classifier: License :: OSI Approved :: MIT License
Classifier: Programming Language :: Python :: 2.7
Classifier: Programming Language :: Python :: 3.5
Requires-Dist: docopt
Requires-Dist: pygame
